<?xml version="1.0" encoding="utf-8"?>
<Dashboard CurrencyCulture="en-US">
  <Title Text="Dashboard" />
  <DataConnections>
    <OlapDataConnection Name="AdventureWorksConnection" ConnectionString="provider=msolap;data source=http://demos.devexpress.com/Services/OLAP/msmdpump.dll;initial catalog=&quot;Adventure Works DW Standard Edition&quot;;timeout=1200;Cube Name=Adventure Works;" />
  </DataConnections>
  <DataSources>
    <DataSource ComponentName="dataSource1" Name="Data Source 1">
      <OlapDataProvider DataConnection="AdventureWorksConnection" />
    </DataSource>
  </DataSources>
  <Items>
    <Card ComponentName="cardDashboardItem1" Name="Cards 1" ShowCaption="false" DataSource="dataSource1">
      <DataItems>
        <Measure DataMember="[Measures].[Sales Amount]" UniqueName="DataItem0">
          <NumericFormat FormatType="Currency" IncludeGroupSeparator="true" />
        </Measure>
        <Dimension DataMember="[Date].[Calendar Quarter of Year].[Calendar Quarter of Year]" UniqueName="DataItem2" />
        <Dimension DataMember="[Date].[Calendar Year].[Calendar Year]" UniqueName="DataItem1" />
      </DataItems>
      <SeriesDimensions>
        <SeriesDimension UniqueName="DataItem1" />
        <SeriesDimension UniqueName="DataItem2" />
      </SeriesDimensions>
      <InteractivityOptions MasterFilterMode="Multiple" />
      <Card>
        <ActualValue UniqueName="DataItem0" />
      </Card>
    </Card>
    <Chart ComponentName="chartDashboardItem1" Name="Chart 1" ShowCaption="false" DataSource="dataSource1">
      <DataItems>
        <Measure DataMember="[Measures].[Sales Amount]" UniqueName="DataItem0">
          <NumericFormat FormatType="Currency" IncludeGroupSeparator="true" />
        </Measure>
        <Dimension DataMember="[Sales Territory].[Sales Territory Country].[Sales Territory Country]" UniqueName="DataItem3" />
      </DataItems>
      <Arguments>
        <Argument UniqueName="DataItem3" />
      </Arguments>
      <Panes>
        <Pane Name="Pane 1">
          <Series>
            <Simple>
              <Value UniqueName="DataItem0" />
            </Simple>
          </Series>
        </Pane>
      </Panes>
    </Chart>
    <Pivot ComponentName="pivotDashboardItem1" Name="Pivot 1" ShowCaption="false" DataSource="dataSource1">
      <DataItems>
        <Dimension DataMember="[Product].[Product Categories].[Subcategory]" GroupIndex="10" UniqueName="DataItem1" />
        <Dimension DataMember="[Product].[Product Categories].[Category]" GroupIndex="10" UniqueName="DataItem0" />
        <Dimension DataMember="[Sales Territory].[Sales Territory Country].[Sales Territory Country]" UniqueName="DataItem3" />
        <Measure DataMember="[Measures].[Sales Amount]" UniqueName="DataItem5">
          <NumericFormat FormatType="Currency" IncludeGroupSeparator="true" />
        </Measure>
        <Dimension DataMember="[Product].[Product Categories].[Product]" GroupIndex="10" UniqueName="DataItem2" />
      </DataItems>
      <Columns>
        <Column UniqueName="DataItem3" />
      </Columns>
      <Rows>
        <Row UniqueName="DataItem0" />
        <Row UniqueName="DataItem1" />
        <Row UniqueName="DataItem2" />
      </Rows>
      <Values>
        <Value UniqueName="DataItem5" />
      </Values>
    </Pivot>
  </Items>
  <LayoutTree>
    <LayoutGroup>
      <LayoutItem Weight="32.63654753877276" DashboardItem="cardDashboardItem1" />
      <LayoutGroup Weight="67.36345246122724" Orientation="Vertical">
        <LayoutItem Weight="49.936948297604033" DashboardItem="chartDashboardItem1" />
        <LayoutItem Weight="50.063051702395967" DashboardItem="pivotDashboardItem1" />
      </LayoutGroup>
    </LayoutGroup>
  </LayoutTree>
</Dashboard>